flask_ipinfo.py
Flask_IPInfo-0.0.10.dist-info/DESCRIPTION.rst
Flask_IPInfo-0.0.10.dist-info/METADATA
Flask_IPInfo-0.0.10.dist-info/RECORD
Flask_IPInfo-0.0.10.dist-info/WHEEL
Flask_IPInfo-0.0.10.dist-info/metadata.json
Flask_IPInfo-0.0.10.dist-info/top_level.txt
