Metadata-Version: 2.0
Name: Flask-IPInfo
Version: 0.0.10
Summary: Get IP, ISP, Location, OS from flask request
Home-page: http://github.com/borisliu/flask-ipinfo/
Author: borisliu
Author-email: boris_cn@263.net
License: MIT
Keywords: flask ip address browser
Platform: all
Classifier: Development Status :: 2 - Pre-Alpha
Classifier: Intended Audience :: Developers
Classifier: Topic :: Internet :: WWW/HTTP :: Dynamic Content
Classifier: License :: OSI Approved :: MIT License
Classifier: Operating System :: OS Independent
Classifier: Programming Language :: Python :: 3
Classifier: Programming Language :: Python :: 3.5
Requires-Dist: Flask
